rkd_harbor/__init__.py
rkd_harbor/__main__.py
rkd_harbor/cached_loader.py
rkd_harbor/driver.py
rkd_harbor/exception.py
rkd_harbor/expressions.py
rkd_harbor/formatting.py
rkd_harbor/interface.py
rkd_harbor/service.py
rkd_harbor/test.py
rkd_harbor/deployment/examples/deployment.yml
rkd_harbor/deployment/files/Vagrantfile
rkd_harbor/deployment/files/ansible.cfg
rkd_harbor/deployment/files/harbor.inventory.cfg.j2
rkd_harbor/deployment/files/harbor.playbook.yml.j2
rkd_harbor/deployment/files/requirements.yml
rkd_harbor/deployment/files/roles/.gitkeep
rkd_harbor/internal/makefile.yaml
rkd_harbor/internal/schema/org.riotkit.harbor-deployment-v1.json
rkd_harbor/project/.env-default
rkd_harbor/project/.gitignore
rkd_harbor/project/docker-compose.yml
rkd_harbor/project/apps/README.md
rkd_harbor/project/apps/conf/README.md
rkd_harbor/project/apps/conf/infrastructure.health.yml
rkd_harbor/project/apps/conf/infrastructure.service-discovery.yml
rkd_harbor/project/apps/conf/infrastructure.smtp.yml
rkd_harbor/project/apps/conf/infrastructure.ssl.yml
rkd_harbor/project/apps/conf.dev/README.md
rkd_harbor/project/apps/continuous-deployment/deployer.yml
rkd_harbor/project/apps/healthchecks/checks/.gitkeep
rkd_harbor/project/apps/healthchecks/configured/disk-space.json
rkd_harbor/project/apps/healthchecks/configured/docker-health.json
rkd_harbor/project/apps/healthchecks/configured/smtp_is_listening.json
rkd_harbor/project/apps/profile/gateway.profile.py
rkd_harbor/project/apps/repos-enabled/.gitkeep
rkd_harbor/project/apps/repos-enabled/some-app.sh
rkd_harbor/project/apps/www-data/.gitkeep
rkd_harbor/project/containers/.gitkeep
rkd_harbor/project/containers/README.md
rkd_harbor/project/containers/auth/technical.htpasswd
rkd_harbor/project/containers/backup/bahub.conf.yaml
rkd_harbor/project/containers/backup/cron
rkd_harbor/project/containers/nginx/nginx.tmpl
rkd_harbor/project/containers/nginx/maintenance/host-not-connected.html
rkd_harbor-2.0.3.dist-info/AUTHORS
rkd_harbor-2.0.3.dist-info/LICENSE
rkd_harbor-2.0.3.dist-info/METADATA
rkd_harbor-2.0.3.dist-info/WHEEL
rkd_harbor-2.0.3.dist-info/entry_points.txt
rkd_harbor-2.0.3.dist-info/pbr.json
rkd_harbor-2.0.3.dist-info/top_level.txt
rkd_harbor-2.0.3.dist-info/RECORD
