Metadata-Version: 2.1
Name: rkd-harbor
Version: 2.0.3
Summary: UNKNOWN
Home-page: https://riotkit.org
Author: RiotKit non-profit organization
Author-email: riotkit@riseup.net
License: Apache-2
Keywords: setup,distutils
Platform: UNKNOWN
Classifier: Development Status :: 4 - Beta
Classifier: Environment :: Console
Classifier: Intended Audience :: System Administrators
Classifier: Intended Audience :: Information Technology
Classifier: Natural Language :: English
Classifier: License :: OSI Approved :: Apache Software License
Classifier: Operating System :: OS Independent
Classifier: Topic :: System :: Installation/Setup
Classifier: Topic :: System :: Systems Administration
Classifier: Programming Language :: Python
Requires-Dist: rkd (<2.4,>=2.3.4)
Requires-Dist: rkd-cooperative (<1.1,>=1.0.2)
Requires-Dist: ansible (>=2.8)
